gancio_requests/__init__.py
gancio_requests/__main__.py
gancio_requests/formatting.py
gancio_requests/request.py
gancio_requests-0.1.2.dist-info/LICENSE
gancio_requests-0.1.2.dist-info/WHEEL
gancio_requests-0.1.2.dist-info/METADATA
gancio_requests-0.1.2.dist-info/RECORD
