Metadata-Version: 2.1
Name: gancio-requests
Version: 0.1.2
Summary: Asynchronous functions for making HTTP requests to Gancio istances
Home-page: https://github.com/bendico765/gancio_requests
License: AGPL-3.0-only
Author: Gianluca Morcaldi
Author-email: bendico765@gmail.com
Requires-Python: >=3.10,<4.0
Classifier: License :: OSI Approved :: GNU Affero General Public License v3
Classifier: Programming Language :: Python :: 3
Classifier: Programming Language :: Python :: 3.10
Requires-Dist: aiohttp (>=3.8.1,<4.0.0)
Requires-Dist: aiohttp-client-cache (>=0.7.3,<0.8.0)
Requires-Dist: aiosignal (>=1.2.0,<2.0.0)
Requires-Dist: beautifulsoup4 (>=4.11.1,<5.0.0)
Project-URL: Repository, https://github.com/bendico765/gancio_requests
